NGSF/.version
NGSF/Header_Binnings.py
NGSF/SF_functions.py
NGSF/auxiliary.py
NGSF/error_routines.py
NGSF/get_metadata.py
NGSF/params.py
NGSF/sf_class.py
NGSF-0.0.1.dist-info/METADATA
NGSF-0.0.1.dist-info/WHEEL
NGSF-0.0.1.dist-info/top_level.txt
NGSF-0.0.1.dist-info/RECORD
