Metadata-Version: 2.1
Name: NGSF
Version: 0.0.1
Summary: Next Generation SuperFit in Python
Home-page: https://github.com/samanthagoldwasser25/NGSF
Author: Samantha Goldwasser, Ofer Yaron, Avner Sass, Ido Irani, Avishay Gal-Yam, D. Andrew Howell
Author-email: ofer.yaron@weizmann.ac.il 
License: MIT
Classifier: Programming Language :: Python :: 3.7
Classifier: Programming Language :: Python :: 3.8
Classifier: Programming Language :: Python :: 3.9
Classifier: License :: OSI Approved :: MIT License
Classifier: Operating System :: OS Independent
Requires-Python: >=3.7
Requires-Dist: astropy
Requires-Dist: extinction
Requires-Dist: matplotlib
Requires-Dist: numpy
Requires-Dist: pandas
Requires-Dist: PyAstronomy
Requires-Dist: scipy
